ASCA/ASCA.py
ASCA/__init__.py
ASCA-1.4.dist-info/LICENSE
ASCA-1.4.dist-info/METADATA
ASCA-1.4.dist-info/WHEEL
ASCA-1.4.dist-info/top_level.txt
ASCA-1.4.dist-info/RECORD
