Metadata-Version: 2.1
Name: ASCA
Version: 1.4
Summary: ASCA: ANOVA-simultaneous component analysis
Author: Sin Yong Teng
Author-email: tsyet12@gmail.com
License: BSD 2-Clause
Keywords: Design of Experiments,Chemometrics,Artificial Intelligence
Classifier: Development Status :: 4 - Beta
Classifier: Intended Audience :: Developers
Classifier: Topic :: Software Development :: Build Tools
Classifier: License :: OSI Approved :: BSD License
Classifier: Programming Language :: Python :: 3
Classifier: Programming Language :: Python :: 3.4
Classifier: Programming Language :: Python :: 3.5
Classifier: Programming Language :: Python :: 3.6
License-File: LICENSE
Requires-Dist: scipy
Requires-Dist: matplotlib
Requires-Dist: scikit-learn
Requires-Dist: numpy
